{
  "platform": "tf",
  "language": "hcl",
  "complexity": "expert",
  "turn_type": "single",
  "po_id": "101912146",
  "team": "2",
  "startedAt": "2025-11-17T14:05:18.316Z",
  "subtask": "IaC-Multi-Environment-Management",
  "subject_labels": [
    "Multi-Environment Consistency"
  ],
  "aws_services": [
    "S3 Bucket",
    "CloudFormation",
    "Lambda",
    "EventBridge",
    "CloudWatch LogGroup",
    "VPC"
  ],
  "task_config": {
    "deploy_env": "dev.tfvars"
  },
  "coverage": {
    "lines": 100,
    "branches": 100
  },
  "training_quality": 10,
  "author": "kanishkah-turing",
  "dockerS3Location": ""
}
