{
  "platform": "cdktf",
  "language": "ts",
  "complexity": "expert",
  "turn_type": "single",
  "po_id": "400104",
  "team": "1",
  "startedAt": "2025-10-12T13:12:38.293Z",
  "subtask": "Provisioning of Infrastructure Environments",
  "subject_labels": [
    "Cloud Environment Setup"
  ],
  "aws_services": [
    "VPC",
    "Subnet",
    "Internet Gateway",
    "Route Table",
    "S3",
    "IAM",
    "Security Groups",
    "CloudWatch Logs"
  ],
  "training_quality": 6,
  "coverage": {
    "lines": 100,
    "branches": 100
  },
  "author": "harshita-turing",
  "dockerS3Location": ""
}
