{
  "platform": "pulumi",
  "language": "py",
  "complexity": "expert",
  "turn_type": "single",
  "team": "synth",
  "author": "mayanksethi-turing",
  "startedAt": "2025-11-18T20:03:00+05:30",
  "subtask": "Application Deployment",
  "subject_labels": [
    "Web Application Deployment"
  ],
  "po_id": "z0f1r0",
  "aws_services": [
    "API Gateway",
    "Lambda",
    "DynamoDB",
    "SQS",
    "SNS",
    "CloudWatch",
    "X-Ray",
    "VPC",
    "VPC Endpoints",
    "KMS",
    "WAF",
    "IAM",
    "EC2"
  ],
  "training_quality": 10,
  "coverage": {
    "lines": 100,
    "branches": 100
  },
  "dockerS3Location": ""
}
