{
  "platform": "tf",
  "language": "hcl",
  "complexity": "hard",
  "turn_type": "single",
  "po_id": "333561",
  "team": "6",
  "startedAt": "2025-10-09T09:09:54.263Z",
  "subtask": "Provisioning of Infrastructure Environments",
  "subject_labels": [
    "Cloud Environment Setup"
  ],
  "aws_services": [
    "VPC",
    "EC2",
    "Auto Scaling",
    "Application Load Balancer",
    "RDS",
    "S3",
    "KMS",
    "IAM",
    "CloudWatch",
    "WAF",
    "ACM"
  ],
  "training_quality": 8,
  "coverage": {
    "lines": 100,
    "branches": 100
  },
  "author": "enyachoke-turing",
  "dockerS3Location": ""
}
