{
  "platform": "cdk",
  "language": "ts",
  "complexity": "hard",
  "turn_type": "single",
  "po_id": "349459",
  "team": "2",
  "startedAt": "2025-10-20T10:59:06.658Z",
  "subtask": "Provisioning of Infrastructure Environments",
  "subject_labels": [
    "Cloud Environment Setup"
  ],
  "background": "Deploy serverless infrastructure with Lambda, API Gateway, DynamoDB, S3, SQS, SSM for RESTful API with monitoring and security best practices",
  "training_quality": 8,
  "aws_services": [
    "Lambda",
    "API Gateway",
    "DynamoDB",
    "S3",
    "SQS",
    "SSM Parameter Store",
    "CloudWatch Logs",
    "X-Ray",
    "IAM"
  ],
  "coverage": {
    "lines": 100,
    "branches": 100
  },
  "author": "Olatunjym",
  "dockerS3Location": ""
}
